{
  "project_info": {
    "project_number": "242846413370",
    "project_id": "laundry-app-c0e5b",
    "storage_bucket": "laundry-app-c0e5b.appspot.com"
  },
  "client": [
    {
      "client_info": {
        "mobilesdk_app_id": "1:242846413370:android:21b63a1b747e8df7a67b03",
        "android_client_info": {
          "package_name": "com.example.app"
        }
      },
      "oauth_client": [],
      "api_key": [
        {
          "current_key": "AIzaSyB_1q65v4vMibqwijjPePkiNZNfVdfC7Lw"
        }
      ],
      "services": {
        "appinvite_service": {
          "other_platform_oauth_client": []
        }
      }
    }
  ],
  "configuration_version": "1"
}